README.txt
setup.cfg
setup.py
korgws/__init__.py
korgws/api.py
korgws/constants.py
korgws/handlers.py
korgws/release.py
korgws/util.py
korgws/scripts/__init__.py
korgws/scripts/listbanks.py
korgwslib.egg-info/PKG-INFO
korgwslib.egg-info/SOURCES.txt
korgwslib.egg-info/dependency_links.txt
korgwslib.egg-info/entry_points.txt
korgwslib.egg-info/not-zip-safe
korgwslib.egg-info/top_level.txt
scripts/wslistbanks.py