Metadata-Version: 1.0
Name: korgwslib
Version: 0.1a
Summary: Korg Wavestation Sysex handling library
Home-page: http://chrisarndt.de/projects/korgwslib
Author: Christopher Arndt
Author-email: chris@chrisarndt.de
License: MIT
Download-URL: http://chrisarndt.de/projects/korgwslib/download/
Platform: UNKNOWN
Classifier: Development Status :: 3 - Alpha
Classifier: Environment :: Console
Classifier: Intended Audience :: Developers
Classifier: License :: OSI Approved :: MIT License
Classifier: Operating System :: OS Independent
Classifier: Programming Language :: Python
Classifier: Topic :: Software Development :: Libraries :: Python Modules
